pygments_style_ssms/__init__.py
pygments_style_ssms/ssms.py
pygments_style_ssms-0.5.dist-info/LICENSE
pygments_style_ssms-0.5.dist-info/METADATA
pygments_style_ssms-0.5.dist-info/WHEEL
pygments_style_ssms-0.5.dist-info/entry_points.txt
pygments_style_ssms-0.5.dist-info/top_level.txt
pygments_style_ssms-0.5.dist-info/RECORD
